aws_ssm_env/__init__.py
aws_ssm_env/ssm.py
aws_ssm_env-0.1.4.dist-info/METADATA
aws_ssm_env-0.1.4.dist-info/WHEEL
aws_ssm_env-0.1.4.dist-info/RECORD
