Metadata-Version: 2.3
Name: aws-ssm-env
Version: 0.1.4
Summary: A lightweight utility to fetch AWS SSM parameters and inject them as environment variables using JSON.
License: MIT
Keywords: aws,ssm,environment,parameter-store,boto3
Author: Angelo Antu
Author-email: angelo.antu@kireap.com
Requires-Python: >=3.10
Classifier: License :: OSI Approved :: MIT License
Classifier: Programming Language :: Python :: 3
Classifier: Programming Language :: Python :: 3.10
Classifier: Programming Language :: Python :: 3.11
Classifier: Programming Language :: Python :: 3.12
Classifier: Programming Language :: Python :: 3.13
Requires-Dist: aioboto3
Requires-Dist: aiobotocore
Requires-Dist: boto3
